{
  "BakeInfoLayouts": [
    {
      "UniqueName": "Monster_W2_Abomi01_00_BeingHit",
      "Offset": 5536
    },
    {
      "UniqueName": "Monster_W2_Abomi01_00_DanHeng_Hide",
      "Offset": 5583
    },
    {
      "UniqueName": "Monster_W2_Abomi01_00_Revive",
      "Offset": 5616
    },
    {
      "UniqueName": "Monster_W2_Abomi01_00_LockHP",
      "Offset": 7127
    },
    {
      "UniqueName": "Monster_W2_Abomi01_00_Accelerate",
      "Offset": 7178
    },
    {
      "UniqueName": "Monster_W2_Abomi01_00_Passive01",
      "TypeId": "TypeId_TurnBasedAbilityConfig",
      "Offset": 2
    },
    {
      "UniqueName": "Monster_W2_Abomi01_00_PassiveSkill_Insert_Phase01",
      "TypeId": "TypeId_TurnBasedAbilityConfig",
      "Offset": 1275
    },
    {
      "UniqueName": "Monster_W2_Abomi01_00_PassiveSkill_Insert02_Phase00",
      "TypeId": "TypeId_TurnBasedAbilityConfig",
      "Offset": 1370
    },
    {
      "UniqueName": "Monster_W2_Abomi01_00_PassiveSkill_Insert02_Phase01",
      "TypeId": "TypeId_TurnBasedAbilityConfig",
      "Offset": 1503
    },
    {
      "UniqueName": "Monster_W2_Abomi01_00_Skill01_Phase01",
      "TypeId": "TypeId_TurnBasedAbilityConfig",
      "Offset": 3451
    },
    {
      "UniqueName": "Monster_W2_Abomi01_00_Skill01_Phase02",
      "TypeId": "TypeId_TurnBasedAbilityConfig",
      "Offset": 3712
    },
    {
      "UniqueName": "Monster_W2_Abomi01_00_Skill02_Phase01",
      "TypeId": "TypeId_TurnBasedAbilityConfig",
      "Offset": 4473
    },
    {
      "UniqueName": "Monster_W2_Abomi01_00_Skill02_Phase02",
      "TypeId": "TypeId_TurnBasedAbilityConfig",
      "Offset": 4734
    }
  ]
}