{
  "BakeInfoLayouts": [
    {
      "UniqueName": "MAvatar_Kafka_00_Passive_CanAttackCD",
      "Offset": 10237
    },
    {
      "UniqueName": "MAvatar_Kafka_00_Rank04",
      "Offset": 10267,
      "Dependency": [
        "MAvatar_Kafka_00_Rank04_Sub"
      ]
    },
    {
      "UniqueName": "MAvatar_Kafka_00_Rank04_Sub",
      "Offset": 10370
    },
    {
      "UniqueName": "Avatar_Kafka_00_Skill01_Phase01",
      "TypeId": "TypeId_TurnBasedAbilityConfig",
      "Offset": 2
    },
    {
      "UniqueName": "Avatar_Kafka_00_Skill01_Phase02",
      "TypeId": "TypeId_TurnBasedAbilityConfig",
      "Offset": 370
    },
    {
      "UniqueName": "Avatar_Kafka_00_Skill02_Phase01",
      "TypeId": "TypeId_TurnBasedAbilityConfig",
      "Offset": 903
    },
    {
      "UniqueName": "Avatar_Kafka_00_Skill02_Phase02",
      "TypeId": "TypeId_TurnBasedAbilityConfig",
      "Offset": 1373
    },
    {
      "UniqueName": "Avatar_Kafka_00_Skill03_EnterReady",
      "TypeId": "TypeId_TurnBasedAbilityConfig",
      "Offset": 2702
    },
    {
      "UniqueName": "Avatar_Kafka_00_Skill03_Phase01",
      "TypeId": "TypeId_TurnBasedAbilityConfig",
      "Offset": 3028
    },
    {
      "UniqueName": "Avatar_Kafka_00_Skill03_Phase02",
      "TypeId": "TypeId_TurnBasedAbilityConfig",
      "Offset": 3255
    },
    {
      "UniqueName": "Avatar_Kafka_00_PassiveSkill01",
      "TypeId": "TypeId_TurnBasedAbilityConfig",
      "Offset": 4015
    },
    {
      "UniqueName": "Avatar_Kafka_00_PassiveAtk_Ability",
      "TypeId": "TypeId_TurnBasedAbilityConfig",
      "Offset": 6759
    },
    {
      "UniqueName": "Avatar_Kafka_SkillTree02",
      "TypeId": "TypeId_TurnBasedAbilityConfig",
      "Offset": 8826
    },
    {
      "UniqueName": "Avatar_Kafka_SkillTree01",
      "TypeId": "TypeId_TurnBasedAbilityConfig",
      "Offset": 9031
    },
    {
      "UniqueName": "Avatar_Kafka_Rank02",
      "TypeId": "TypeId_TurnBasedAbilityConfig",
      "Offset": 9062
    },
    {
      "UniqueName": "Avatar_Kafka_00_SkillMazeInLevel",
      "TypeId": "TypeId_TurnBasedAbilityConfig",
      "Offset": 9455
    }
  ]
}