[
  {
    "ID": 10010101,
    "Sentence": {
      "Hash": 13507939961766361359
    },
    "VoiceID": 80101001
  },
  {
    "ID": 10010102,
    "Sentence": {
      "Hash": 6136807388130414166
    },
    "VoiceID": 80101002
  },
  {
    "ID": 10010103,
    "Sentence": {
      "Hash": 10064012614730494235
    },
    "VoiceID": 80101003
  },
  {
    "ID": 10010104,
    "Sentence": {
      "Hash": 15525649124783587457
    },
    "VoiceID": 80101004
  },
  {
    "ID": 10010201,
    "Sentence": {
      "Hash": 7150938310409301981
    },
    "VoiceID": 80101005
  },
  {
    "ID": 10010202,
    "Sentence": {
      "Hash": 11318317252953512559
    },
    "VoiceID": 80101006
  },
  {
    "ID": 10010203,
    "Sentence": {
      "Hash": 1224625496470705015
    },
    "VoiceID": 80101007
  },
  {
    "ID": 10010204,
    "Sentence": {
      "Hash": 3680128827842754453
    },
    "VoiceID": 80101008
  },
  {
    "ID": 10010212,
    "Sentence": {
      "Hash": 3675425874220488119
    },
    "VoiceID": 80101006
  },
  {
    "ID": 10010214,
    "Sentence": {
      "Hash": 6543151141560219256
    },
    "VoiceID": 80101008
  },
  {
    "ID": 10010301,
    "Sentence": {
      "Hash": 6999589970196326958
    },
    "VoiceID": 80101009
  },
  {
    "ID": 10010302,
    "Sentence": {
      "Hash": 17522445298793923064
    },
    "VoiceID": 80101010
  },
  {
    "ID": 10010303,
    "Sentence": {
      "Hash": 5675211687626709329
    },
    "VoiceID": 80101011
  },
  {
    "ID": 10010304,
    "Sentence": {
      "Hash": 304791487291861860
    },
    "VoiceID": 80101012
  },
  {
    "ID": 10010312,
    "Sentence": {
      "Hash": 11522914446283883183
    },
    "VoiceID": 80101010
  },
  {
    "ID": 10010401,
    "Sentence": {
      "Hash": 12870240392252390848
    },
    "VoiceID": 80101013
  },
  {
    "ID": 10010402,
    "Sentence": {
      "Hash": 9954092390781185608
    },
    "VoiceID": 80101014
  },
  {
    "ID": 10010403,
    "Sentence": {
      "Hash": 16385582697041649884
    },
    "VoiceID": 80101015
  },
  {
    "ID": 10010404,
    "Sentence": {
      "Hash": 1763246519891142569
    },
    "VoiceID": 80101016
  },
  {
    "ID": 10010405,
    "Sentence": {
      "Hash": 18129426917585510272
    },
    "VoiceID": 80101017
  },
  {
    "ID": 10010501,
    "Sentence": {
      "Hash": 11353046861178380658
    },
    "VoiceID": 80101018
  },
  {
    "ID": 10010502,
    "Sentence": {
      "Hash": 14644803414402245324
    },
    "VoiceID": 80101019
  },
  {
    "ID": 10010503,
    "Sentence": {
      "Hash": 3516749050542674330
    },
    "VoiceID": 80101020
  },
  {
    "ID": 10010504,
    "Sentence": {
      "Hash": 8833362886052239850
    },
    "VoiceID": 80101021
  },
  {
    "ID": 7010101,
    "Sentence": {
      "Hash": 14508265034547616078
    },
    "VoiceID": 80071001
  },
  {
    "ID": 7010102,
    "Sentence": {
      "Hash": 4688007556881947249
    },
    "VoiceID": 80071002
  },
  {
    "ID": 7010103,
    "Sentence": {
      "Hash": 2470689113508201542
    },
    "VoiceID": 80071003
  },
  {
    "ID": 7010104,
    "Sentence": {
      "Hash": 15306188796998812544
    },
    "VoiceID": 80071004
  },
  {
    "ID": 7010114,
    "Sentence": {
      "Hash": 8954871077894230987
    },
    "VoiceID": 80071004
  },
  {
    "ID": 7010201,
    "Sentence": {
      "Hash": 1211082100825662441
    },
    "VoiceID": 80071005
  },
  {
    "ID": 7010202,
    "Sentence": {
      "Hash": 5358756344764906925
    },
    "VoiceID": 80071006
  },
  {
    "ID": 7010203,
    "Sentence": {
      "Hash": 17074912543259032203
    },
    "VoiceID": 80071007
  },
  {
    "ID": 7010204,
    "Sentence": {
      "Hash": 142094725486821125
    },
    "VoiceID": 80071008
  },
  {
    "ID": 7010205,
    "Sentence": {
      "Hash": 17626248113043287322
    },
    "VoiceID": 80071009
  },
  {
    "ID": 7010301,
    "Sentence": {
      "Hash": 7239206824737023396
    },
    "VoiceID": 80071010
  },
  {
    "ID": 7010302,
    "Sentence": {
      "Hash": 10358537825716984617
    },
    "VoiceID": 80071011
  },
  {
    "ID": 7010303,
    "Sentence": {
      "Hash": 6177746362887270550
    },
    "VoiceID": 80071012
  },
  {
    "ID": 7010304,
    "Sentence": {
      "Hash": 4785314721090719235
    },
    "VoiceID": 80071013
  },
  {
    "ID": 7010305,
    "Sentence": {
      "Hash": 14422327485180595201
    },
    "VoiceID": 80071014
  },
  {
    "ID": 7010401,
    "Sentence": {
      "Hash": 4151323162418844361
    },
    "VoiceID": 80071015
  },
  {
    "ID": 7010402,
    "Sentence": {
      "Hash": 16115381647584187105
    },
    "VoiceID": 80071016
  },
  {
    "ID": 7010403,
    "Sentence": {
      "Hash": 3866740554892749997
    },
    "VoiceID": 80071017
  },
  {
    "ID": 7010404,
    "Sentence": {
      "Hash": 12614729658522999875
    },
    "VoiceID": 80071018
  },
  {
    "ID": 7010501,
    "Sentence": {
      "Hash": 16714159533817017733
    },
    "VoiceID": 80071019
  },
  {
    "ID": 7010502,
    "Sentence": {
      "Hash": 7691657444510688514
    },
    "VoiceID": 80071020
  },
  {
    "ID": 7010503,
    "Sentence": {
      "Hash": 16523974485236855833
    },
    "VoiceID": 80071021
  },
  {
    "ID": 7010504,
    "Sentence": {
      "Hash": 5233679126815693142
    },
    "VoiceID": 80071022
  },
  {
    "ID": 7010505,
    "Sentence": {
      "Hash": 2741751981375975762
    },
    "VoiceID": 80071023
  },
  {
    "ID": 1010101,
    "Sentence": {
      "Hash": 15431721484140346210
    },
    "VoiceID": 80011001
  },
  {
    "ID": 1010102,
    "Sentence": {
      "Hash": 7191066246828058734
    },
    "VoiceID": 80011002
  },
  {
    "ID": 1010103,
    "Sentence": {
      "Hash": 17798366281588517297
    },
    "VoiceID": 80011003
  },
  {
    "ID": 1010104,
    "Sentence": {
      "Hash": 10928471440061370258
    },
    "VoiceID": 80011004
  },
  {
    "ID": 1010201,
    "Sentence": {
      "Hash": 3416374424566864146
    },
    "VoiceID": 80011005
  },
  {
    "ID": 1010202,
    "Sentence": {
      "Hash": 7395091770959157864
    },
    "VoiceID": 80011006
  },
  {
    "ID": 1010203,
    "Sentence": {
      "Hash": 18390991434170498451
    },
    "VoiceID": 80011007
  },
  {
    "ID": 1010204,
    "Sentence": {
      "Hash": 15145693710873235992
    },
    "VoiceID": 80011008
  },
  {
    "ID": 1010205,
    "Sentence": {
      "Hash": 4519011333353146489
    },
    "VoiceID": 80011009
  },
  {
    "ID": 1010301,
    "Sentence": {
      "Hash": 17494266833460117128
    },
    "VoiceID": 80011010
  },
  {
    "ID": 1010302,
    "Sentence": {
      "Hash": 2580611375919771824
    },
    "VoiceID": 80011011
  },
  {
    "ID": 1010303,
    "Sentence": {
      "Hash": 3294960331933611404
    },
    "VoiceID": 80011012
  },
  {
    "ID": 1010304,
    "Sentence": {
      "Hash": 17218977252964572831
    },
    "VoiceID": 80011013
  },
  {
    "ID": 1010313,
    "Sentence": {
      "Hash": 353005576510989561
    },
    "VoiceID": 80011012
  },
  {
    "ID": 1010314,
    "Sentence": {
      "Hash": 8157998407662508422
    },
    "VoiceID": 80011013
  },
  {
    "ID": 1010401,
    "Sentence": {
      "Hash": 2428612654976947103
    },
    "VoiceID": 80011014
  },
  {
    "ID": 1010402,
    "Sentence": {
      "Hash": 5721636794856906822
    },
    "VoiceID": 80011015
  },
  {
    "ID": 1010403,
    "Sentence": {
      "Hash": 1374379969419172506
    },
    "VoiceID": 80011016
  },
  {
    "ID": 1010404,
    "Sentence": {
      "Hash": 10215336774741107021
    },
    "VoiceID": 80011017
  },
  {
    "ID": 1010405,
    "Sentence": {
      "Hash": 11463379848604618521
    },
    "VoiceID": 80011018
  },
  {
    "ID": 1010412,
    "Sentence": {
      "Hash": 4848794255771705477
    },
    "VoiceID": 80011015
  },
  {
    "ID": 1010413,
    "Sentence": {
      "Hash": 13304340914171148264
    },
    "VoiceID": 80011016
  },
  {
    "ID": 1010414,
    "Sentence": {
      "Hash": 3262146396968278003
    },
    "VoiceID": 80011017
  },
  {
    "ID": 1010501,
    "Sentence": {
      "Hash": 17594841700201126235
    },
    "VoiceID": 80011019
  },
  {
    "ID": 1010502,
    "Sentence": {
      "Hash": 7844878722842574012
    },
    "VoiceID": 80011020
  },
  {
    "ID": 1010503,
    "Sentence": {
      "Hash": 11482695376379263365
    },
    "VoiceID": 80011021
  },
  {
    "ID": 1010504,
    "Sentence": {
      "Hash": 6770976366577015708
    },
    "VoiceID": 80011022
  },
  {
    "ID": 1010505,
    "Sentence": {
      "Hash": 10005552299760290501
    },
    "VoiceID": 80011023
  },
  {
    "ID": 1020101,
    "Sentence": {
      "Hash": 8959827504887865434
    },
    "VoiceID": 80012001
  },
  {
    "ID": 1020102,
    "Sentence": {
      "Hash": 3120379724133932889
    },
    "VoiceID": 80012002
  },
  {
    "ID": 1020103,
    "Sentence": {
      "Hash": 11758480615200669064
    },
    "VoiceID": 80012003
  },
  {
    "ID": 1020104,
    "Sentence": {
      "Hash": 7261549135046849906
    },
    "VoiceID": 80012004
  },
  {
    "ID": 1020201,
    "Sentence": {
      "Hash": 2059999617892248365
    },
    "VoiceID": 80012005
  },
  {
    "ID": 1020202,
    "Sentence": {
      "Hash": 12158551417556524234
    },
    "VoiceID": 80012006
  },
  {
    "ID": 1020203,
    "Sentence": {
      "Hash": 17180033767035355497
    },
    "VoiceID": 80012007
  },
  {
    "ID": 1020204,
    "Sentence": {
      "Hash": 1849879645215522304
    },
    "VoiceID": 80012008
  },
  {
    "ID": 1020301,
    "Sentence": {
      "Hash": 11298910349420248400
    },
    "VoiceID": 80012009
  },
  {
    "ID": 1020302,
    "Sentence": {
      "Hash": 14761410732876813886
    },
    "VoiceID": 80012010
  },
  {
    "ID": 1020303,
    "Sentence": {
      "Hash": 1691151610629124549
    },
    "VoiceID": 80012011
  },
  {
    "ID": 1020304,
    "Sentence": {
      "Hash": 6404249464232950288
    },
    "VoiceID": 80012012
  },
  {
    "ID": 1020305,
    "Sentence": {
      "Hash": 11110305816755653023
    },
    "VoiceID": 80012013
  },
  {
    "ID": 1020306,
    "Sentence": {
      "Hash": 10397409736873938190
    },
    "VoiceID": 80012014
  },
  {
    "ID": 1020401,
    "Sentence": {
      "Hash": 16496774242257407788
    },
    "VoiceID": 80012015
  },
  {
    "ID": 1020402,
    "Sentence": {
      "Hash": 4288501715275251679
    },
    "VoiceID": 80012016
  },
  {
    "ID": 1020403,
    "Sentence": {
      "Hash": 973082793814472819
    },
    "VoiceID": 80012017
  },
  {
    "ID": 1020404,
    "Sentence": {
      "Hash": 115212843389643355
    },
    "VoiceID": 80012018
  },
  {
    "ID": 1020501,
    "Sentence": {
      "Hash": 18304129306665222317
    },
    "VoiceID": 80012019
  },
  {
    "ID": 1020502,
    "Sentence": {
      "Hash": 4298025768329000104
    },
    "VoiceID": 80012020
  },
  {
    "ID": 1020503,
    "Sentence": {
      "Hash": 4239557552365020753
    },
    "VoiceID": 80012021
  },
  {
    "ID": 1020504,
    "Sentence": {
      "Hash": 9713519072490222201
    },
    "VoiceID": 80012022
  },
  {
    "ID": 1020511,
    "Sentence": {
      "Hash": 3353357297898211533
    },
    "VoiceID": 80012019
  },
  {
    "ID": 1020512,
    "Sentence": {
      "Hash": 13424769355588819441
    },
    "VoiceID": 80012020
  },
  {
    "ID": 9010101,
    "Sentence": {
      "Hash": 8669751230179634115
    },
    "VoiceID": 80091001
  },
  {
    "ID": 9010102,
    "Sentence": {
      "Hash": 13109471598495152076
    },
    "VoiceID": 80091002
  },
  {
    "ID": 9010103,
    "Sentence": {
      "Hash": 273343052108073363
    },
    "VoiceID": 80091003
  },
  {
    "ID": 9010104,
    "Sentence": {
      "Hash": 896635000534645758
    },
    "VoiceID": 80091004
  },
  {
    "ID": 9010201,
    "Sentence": {
      "Hash": 15323088570708239592
    },
    "VoiceID": 80091005
  },
  {
    "ID": 9010202,
    "Sentence": {
      "Hash": 1356613952389990102
    },
    "VoiceID": 80091006
  },
  {
    "ID": 9010203,
    "Sentence": {
      "Hash": 5803929566075079436
    },
    "VoiceID": 80091007
  },
  {
    "ID": 9010204,
    "Sentence": {
      "Hash": 9495527158761011000
    },
    "VoiceID": 80091008
  },
  {
    "ID": 9010301,
    "Sentence": {
      "Hash": 3198292409909740426
    },
    "VoiceID": 80091009
  },
  {
    "ID": 9010302,
    "Sentence": {
      "Hash": 3212596732103550660
    },
    "VoiceID": 80091010
  },
  {
    "ID": 9010303,
    "Sentence": {
      "Hash": 2157481994573704863
    },
    "VoiceID": 80091011
  },
  {
    "ID": 9010304,
    "Sentence": {
      "Hash": 9427158529366308344
    },
    "VoiceID": 80091012
  },
  {
    "ID": 9010401,
    "Sentence": {
      "Hash": 4940175125510921597
    },
    "VoiceID": 80091013
  },
  {
    "ID": 9010402,
    "Sentence": {
      "Hash": 4684806456599566183
    },
    "VoiceID": 80091014
  },
  {
    "ID": 9010403,
    "Sentence": {
      "Hash": 17279648606457446388
    },
    "VoiceID": 80091015
  },
  {
    "ID": 9010404,
    "Sentence": {
      "Hash": 14849662197956789924
    },
    "VoiceID": 80091016
  },
  {
    "ID": 9010405,
    "Sentence": {
      "Hash": 18194459509539061909
    },
    "VoiceID": 80091017
  },
  {
    "ID": 9010501,
    "Sentence": {
      "Hash": 879914714210106134
    },
    "VoiceID": 80091018
  },
  {
    "ID": 9010502,
    "Sentence": {
      "Hash": 5227584778000969798
    },
    "VoiceID": 80091019
  },
  {
    "ID": 9010503,
    "Sentence": {
      "Hash": 6254308857689352850
    },
    "VoiceID": 80091020
  },
  {
    "ID": 9010504,
    "Sentence": {
      "Hash": 6966397725199398355
    },
    "VoiceID": 80091021
  },
  {
    "ID": 9020101,
    "Sentence": {
      "Hash": 7109440060481231851
    },
    "VoiceID": 80092001
  },
  {
    "ID": 9020102,
    "Sentence": {
      "Hash": 17541146141760031271
    },
    "VoiceID": 80092002
  },
  {
    "ID": 9020103,
    "Sentence": {
      "Hash": 16142618345787170101
    },
    "VoiceID": 80092003
  },
  {
    "ID": 9020104,
    "Sentence": {
      "Hash": 9028634918064125037
    },
    "VoiceID": 80092004
  },
  {
    "ID": 9020201,
    "Sentence": {
      "Hash": 15348607845882661129
    },
    "VoiceID": 80092005
  },
  {
    "ID": 9020202,
    "Sentence": {
      "Hash": 221155363886554634
    },
    "VoiceID": 80092006
  },
  {
    "ID": 9020203,
    "Sentence": {
      "Hash": 10840125620181315457
    },
    "VoiceID": 80092007
  },
  {
    "ID": 9020204,
    "Sentence": {
      "Hash": 17228234003344284215
    },
    "VoiceID": 80092008
  },
  {
    "ID": 9020211,
    "Sentence": {
      "Hash": 13918732460773385969
    },
    "VoiceID": 80092005
  },
  {
    "ID": 9020301,
    "Sentence": {
      "Hash": 15699518154313799568
    },
    "VoiceID": 80092009
  },
  {
    "ID": 9020302,
    "Sentence": {
      "Hash": 14413900254123085329
    },
    "VoiceID": 80092010
  },
  {
    "ID": 9020303,
    "Sentence": {
      "Hash": 13563125202120606075
    },
    "VoiceID": 80092011
  },
  {
    "ID": 9020304,
    "Sentence": {
      "Hash": 13973921343469875789
    },
    "VoiceID": 80092012
  },
  {
    "ID": 9020312,
    "Sentence": {
      "Hash": 5734810049545344046
    },
    "VoiceID": 80092010
  },
  {
    "ID": 9020401,
    "Sentence": {
      "Hash": 9082289164092789800
    },
    "VoiceID": 80092013
  },
  {
    "ID": 9020402,
    "Sentence": {
      "Hash": 1849590094997852941
    },
    "VoiceID": 80092014
  },
  {
    "ID": 9020403,
    "Sentence": {
      "Hash": 12791478047565286128
    },
    "VoiceID": 80092015
  },
  {
    "ID": 9020404,
    "Sentence": {
      "Hash": 396954600739340156
    },
    "VoiceID": 80092016
  },
  {
    "ID": 9020501,
    "Sentence": {
      "Hash": 6482444332931176247
    },
    "VoiceID": 80092017
  },
  {
    "ID": 9020502,
    "Sentence": {
      "Hash": 526230905963297324
    },
    "VoiceID": 80092018
  },
  {
    "ID": 9020503,
    "Sentence": {
      "Hash": 8321441020429206641
    },
    "VoiceID": 80092019
  },
  {
    "ID": 9020504,
    "Sentence": {
      "Hash": 870261480662744773
    },
    "VoiceID": 80092020
  },
  {
    "ID": 1030101,
    "Sentence": {
      "Hash": 10130587057571950035
    },
    "VoiceID": 80013001
  },
  {
    "ID": 1030102,
    "Sentence": {
      "Hash": 8099475789886816933
    },
    "VoiceID": 80013002
  },
  {
    "ID": 1030103,
    "Sentence": {
      "Hash": 4488713369375887821
    },
    "VoiceID": 80013003
  },
  {
    "ID": 1030201,
    "Sentence": {
      "Hash": 5521236793394737177
    },
    "VoiceID": 80013004
  },
  {
    "ID": 1030202,
    "Sentence": {
      "Hash": 5086182073870734313
    },
    "VoiceID": 80013005
  },
  {
    "ID": 1030203,
    "Sentence": {
      "Hash": 1258046032439066240
    },
    "VoiceID": 80013006
  },
  {
    "ID": 1030204,
    "Sentence": {
      "Hash": 184449635997368327
    },
    "VoiceID": 80013007
  },
  {
    "ID": 1030301,
    "Sentence": {
      "Hash": 13689213409582244044
    },
    "VoiceID": 80013008
  },
  {
    "ID": 1030302,
    "Sentence": {
      "Hash": 18290460167993491716
    },
    "VoiceID": 80013009
  },
  {
    "ID": 1030303,
    "Sentence": {
      "Hash": 12257829751260187081
    },
    "VoiceID": 80013010
  },
  {
    "ID": 1030304,
    "Sentence": {
      "Hash": 13591127412748356965
    },
    "VoiceID": 80013011
  },
  {
    "ID": 1030401,
    "Sentence": {
      "Hash": 7262608052399627745
    },
    "VoiceID": 80013012
  },
  {
    "ID": 1030402,
    "Sentence": {
      "Hash": 1113766263312164357
    },
    "VoiceID": 80013013
  },
  {
    "ID": 1030403,
    "Sentence": {
      "Hash": 14108422515660328515
    },
    "VoiceID": 80013014
  },
  {
    "ID": 1030404,
    "Sentence": {
      "Hash": 16221848621563852367
    },
    "VoiceID": 80013015
  },
  {
    "ID": 1030405,
    "Sentence": {
      "Hash": 16127324013755755578
    },
    "VoiceID": 80013016
  },
  {
    "ID": 1030501,
    "Sentence": {
      "Hash": 17300039665824120033
    },
    "VoiceID": 80013017
  },
  {
    "ID": 1030502,
    "Sentence": {
      "Hash": 4834381518501815025
    },
    "VoiceID": 80013018
  },
  {
    "ID": 1030503,
    "Sentence": {
      "Hash": 15985433255693683647
    },
    "VoiceID": 80013019
  },
  {
    "ID": 1030504,
    "Sentence": {
      "Hash": 16583907837197819969
    },
    "VoiceID": 80013020
  },
  {
    "ID": 1030505,
    "Sentence": {
      "Hash": 17520788803266653692
    },
    "VoiceID": 80013021
  },
  {
    "ID": 1030506,
    "Sentence": {
      "Hash": 13306839350315642951
    },
    "VoiceID": 80013022
  },
  {
    "ID": 1040101,
    "Sentence": {
      "Hash": 6007802047913155885
    },
    "VoiceID": 80014001
  },
  {
    "ID": 1040102,
    "Sentence": {
      "Hash": 2645345386076447259
    },
    "VoiceID": 80014002
  },
  {
    "ID": 1040103,
    "Sentence": {
      "Hash": 824428189017238558
    },
    "VoiceID": 80014003
  },
  {
    "ID": 1040104,
    "Sentence": {
      "Hash": 4140862447466694683
    },
    "VoiceID": 80014004
  },
  {
    "ID": 1040201,
    "Sentence": {
      "Hash": 9731775291271600146
    },
    "VoiceID": 80014005
  },
  {
    "ID": 1040202,
    "Sentence": {
      "Hash": 2876216741919712255
    },
    "VoiceID": 80014006
  },
  {
    "ID": 1040203,
    "Sentence": {
      "Hash": 15213807792870365365
    },
    "VoiceID": 80014007
  },
  {
    "ID": 1040301,
    "Sentence": {
      "Hash": 15824020648172601521
    },
    "VoiceID": 80014008
  },
  {
    "ID": 1040302,
    "Sentence": {
      "Hash": 11545078790294775895
    },
    "VoiceID": 80014009
  },
  {
    "ID": 1040303,
    "Sentence": {
      "Hash": 9430743344695572084
    },
    "VoiceID": 80014010
  },
  {
    "ID": 1040401,
    "Sentence": {
      "Hash": 4209966619209740834
    },
    "VoiceID": 80014011
  },
  {
    "ID": 1040402,
    "Sentence": {
      "Hash": 1351196245312092426
    },
    "VoiceID": 80014012
  },
  {
    "ID": 1040403,
    "Sentence": {
      "Hash": 14295613842127748432
    },
    "VoiceID": 80014013
  },
  {
    "ID": 1040501,
    "Sentence": {
      "Hash": 16394792230096545860
    },
    "VoiceID": 80014014
  },
  {
    "ID": 1040502,
    "Sentence": {
      "Hash": 1586182636573432963
    },
    "VoiceID": 80014015
  },
  {
    "ID": 1040503,
    "Sentence": {
      "Hash": 2477485092230335392
    },
    "VoiceID": 80014016
  },
  {
    "ID": 1040504,
    "Sentence": {
      "Hash": 8353891647408527509
    },
    "VoiceID": 80014017
  },
  {
    "ID": 1040505,
    "Sentence": {
      "Hash": 6929705199427543754
    },
    "VoiceID": 80014018
  },
  {
    "ID": 10020101,
    "Sentence": {
      "Hash": 9342749649511207088
    },
    "VoiceID": 80102001
  },
  {
    "ID": 10020102,
    "Sentence": {
      "Hash": 12730142447140165847
    },
    "VoiceID": 80102002
  },
  {
    "ID": 10020103,
    "Sentence": {
      "Hash": 8887691821263710382
    },
    "VoiceID": 80102003
  },
  {
    "ID": 10020104,
    "Sentence": {
      "Hash": 263408167940492747
    },
    "VoiceID": 80102004
  },
  {
    "ID": 10020201,
    "Sentence": {
      "Hash": 11562252304901561587
    },
    "VoiceID": 80102005
  },
  {
    "ID": 10020202,
    "Sentence": {
      "Hash": 14108036016910666455
    },
    "VoiceID": 80102006
  },
  {
    "ID": 10020203,
    "Sentence": {
      "Hash": 16665076973407457836
    },
    "VoiceID": 80102007
  },
  {
    "ID": 10020204,
    "Sentence": {
      "Hash": 2693359465060975048
    },
    "VoiceID": 80102008
  },
  {
    "ID": 10020205,
    "Sentence": {
      "Hash": 1486249699355657781
    },
    "VoiceID": 80102009
  },
  {
    "ID": 10020301,
    "Sentence": {
      "Hash": 15807722484878309510
    },
    "VoiceID": 80102010
  },
  {
    "ID": 10020302,
    "Sentence": {
      "Hash": 14585240354946652242
    },
    "VoiceID": 80102011
  },
  {
    "ID": 10020303,
    "Sentence": {
      "Hash": 4664217635528683000
    },
    "VoiceID": 80102012
  },
  {
    "ID": 10020304,
    "Sentence": {
      "Hash": 13564102686742375037
    },
    "VoiceID": 80102013
  },
  {
    "ID": 10020401,
    "Sentence": {
      "Hash": 11590442956456019496
    },
    "VoiceID": 80102014
  },
  {
    "ID": 10020402,
    "Sentence": {
      "Hash": 9905117518385979442
    },
    "VoiceID": 80102015
  },
  {
    "ID": 10020403,
    "Sentence": {
      "Hash": 16161768177114669400
    },
    "VoiceID": 80102016
  },
  {
    "ID": 10020501,
    "Sentence": {
      "Hash": 3553536163088729288
    },
    "VoiceID": 80102017
  },
  {
    "ID": 10020502,
    "Sentence": {
      "Hash": 13146133513696700146
    },
    "VoiceID": 80102018
  },
  {
    "ID": 10020503,
    "Sentence": {
      "Hash": 16574735965385425006
    },
    "VoiceID": 80102019
  },
  {
    "ID": 10020504,
    "Sentence": {
      "Hash": 6722082773820889722
    },
    "VoiceID": 80102020
  },
  {
    "ID": 10030101,
    "Sentence": {
      "Hash": 8639313400514537325
    },
    "VoiceID": 80103001
  },
  {
    "ID": 10030102,
    "Sentence": {
      "Hash": 12624513057523587723
    },
    "VoiceID": 80103002
  },
  {
    "ID": 10030103,
    "Sentence": {
      "Hash": 3626313172229642787
    },
    "VoiceID": 80103003
  },
  {
    "ID": 10030104,
    "Sentence": {
      "Hash": 17044567587378825138
    },
    "VoiceID": 80103004
  },
  {
    "ID": 10030201,
    "Sentence": {
      "Hash": 13573741886249485946
    },
    "VoiceID": 80103005
  },
  {
    "ID": 10030202,
    "Sentence": {
      "Hash": 11605876778175976443
    },
    "VoiceID": 80103006
  },
  {
    "ID": 10030203,
    "Sentence": {
      "Hash": 8633834414317301317
    },
    "VoiceID": 80103007
  },
  {
    "ID": 10030204,
    "Sentence": {
      "Hash": 16819614971987455534
    },
    "VoiceID": 80103008
  },
  {
    "ID": 10030301,
    "Sentence": {
      "Hash": 3186112471367276089
    },
    "VoiceID": 80103009
  },
  {
    "ID": 10030302,
    "Sentence": {
      "Hash": 7863771673424389401
    },
    "VoiceID": 80103010
  },
  {
    "ID": 10030303,
    "Sentence": {
      "Hash": 2319660376126973803
    },
    "VoiceID": 80103011
  },
  {
    "ID": 10030304,
    "Sentence": {
      "Hash": 12434651386723374194
    },
    "VoiceID": 80103012
  },
  {
    "ID": 10030401,
    "Sentence": {
      "Hash": 7093514237621531792
    },
    "VoiceID": 80103013
  },
  {
    "ID": 10030402,
    "Sentence": {
      "Hash": 1110886946204746824
    },
    "VoiceID": 80103014
  },
  {
    "ID": 10030403,
    "Sentence": {
      "Hash": 6629076858643475647
    },
    "VoiceID": 80103015
  },
  {
    "ID": 10030404,
    "Sentence": {
      "Hash": 10135464135032075334
    },
    "VoiceID": 80103016
  },
  {
    "ID": 10030501,
    "Sentence": {
      "Hash": 4214319976093185925
    },
    "VoiceID": 80103017
  },
  {
    "ID": 10030502,
    "Sentence": {
      "Hash": 518494721624331360
    },
    "VoiceID": 80103018
  },
  {
    "ID": 10030503,
    "Sentence": {
      "Hash": 1477093857779694331
    },
    "VoiceID": 80103019
  },
  {
    "ID": 10030504,
    "Sentence": {
      "Hash": 5013243067359368894
    },
    "VoiceID": 80103020
  },
  {
    "ID": 8010101,
    "Sentence": {
      "Hash": 9756951941096914312
    },
    "VoiceID": 80081001
  },
  {
    "ID": 8010102,
    "Sentence": {
      "Hash": 17197648423246577156
    },
    "VoiceID": 80081002
  },
  {
    "ID": 8010103,
    "Sentence": {
      "Hash": 2793765571554041343
    },
    "VoiceID": 80081003
  },
  {
    "ID": 8010104,
    "Sentence": {
      "Hash": 9507761303361273054
    },
    "VoiceID": 80081004
  },
  {
    "ID": 8010201,
    "Sentence": {
      "Hash": 13688495475396690182
    },
    "VoiceID": 80081005
  },
  {
    "ID": 8010202,
    "Sentence": {
      "Hash": 7892706933950235361
    },
    "VoiceID": 80081006
  },
  {
    "ID": 8010203,
    "Sentence": {
      "Hash": 15048399456191254956
    },
    "VoiceID": 80081007
  },
  {
    "ID": 8010204,
    "Sentence": {
      "Hash": 993397326837664794
    },
    "VoiceID": 80081008
  },
  {
    "ID": 8010301,
    "Sentence": {
      "Hash": 16160298843762106967
    },
    "VoiceID": 80081009
  },
  {
    "ID": 8010302,
    "Sentence": {
      "Hash": 7102254095275784897
    },
    "VoiceID": 80081010
  },
  {
    "ID": 8010303,
    "Sentence": {
      "Hash": 8612332166456845845
    },
    "VoiceID": 80081011
  },
  {
    "ID": 8010304,
    "Sentence": {
      "Hash": 9854371761544158769
    },
    "VoiceID": 80081012
  },
  {
    "ID": 8010401,
    "Sentence": {
      "Hash": 3486956866784558130
    },
    "VoiceID": 80081013
  },
  {
    "ID": 8010402,
    "Sentence": {
      "Hash": 17617203322719861124
    },
    "VoiceID": 80081014
  },
  {
    "ID": 8010403,
    "Sentence": {
      "Hash": 1216987357873958791
    },
    "VoiceID": 80081015
  },
  {
    "ID": 8010404,
    "Sentence": {
      "Hash": 10801262877527726027
    },
    "VoiceID": 80081016
  },
  {
    "ID": 8010501,
    "Sentence": {
      "Hash": 8733187081552098730
    },
    "VoiceID": 80081017
  },
  {
    "ID": 8010502,
    "Sentence": {
      "Hash": 10321005131333436657
    },
    "VoiceID": 80081018
  },
  {
    "ID": 8010503,
    "Sentence": {
      "Hash": 6921611493606689413
    },
    "VoiceID": 80081019
  },
  {
    "ID": 8010504,
    "Sentence": {
      "Hash": 7120128998189328644
    },
    "VoiceID": 80081020
  },
  {
    "ID": 8010505,
    "Sentence": {
      "Hash": 6905365050821649685
    },
    "VoiceID": 80081021
  },
  {
    "ID": 9030101,
    "Sentence": {
      "Hash": 16744400971441327437
    },
    "VoiceID": 80093001
  },
  {
    "ID": 9030102,
    "Sentence": {
      "Hash": 2474538057854619673
    },
    "VoiceID": 80093002
  },
  {
    "ID": 9030103,
    "Sentence": {
      "Hash": 14608161189374133067
    },
    "VoiceID": 80093003
  },
  {
    "ID": 9030104,
    "Sentence": {
      "Hash": 3447383928578173625
    },
    "VoiceID": 80093004
  },
  {
    "ID": 9030201,
    "Sentence": {
      "Hash": 3567976076656228386
    },
    "VoiceID": 80093005
  },
  {
    "ID": 9030202,
    "Sentence": {
      "Hash": 11314513277897473243
    },
    "VoiceID": 80093006
  },
  {
    "ID": 9030203,
    "Sentence": {
      "Hash": 14583370019899014563
    },
    "VoiceID": 80093007
  },
  {
    "ID": 9030204,
    "Sentence": {
      "Hash": 1690150145686270728
    },
    "VoiceID": 80093008
  },
  {
    "ID": 9030301,
    "Sentence": {
      "Hash": 10636997652879123033
    },
    "VoiceID": 80093009
  },
  {
    "ID": 9030302,
    "Sentence": {
      "Hash": 8689468840668278725
    },
    "VoiceID": 80093010
  },
  {
    "ID": 9030303,
    "Sentence": {
      "Hash": 8526777792446031018
    },
    "VoiceID": 80093011
  },
  {
    "ID": 9030401,
    "Sentence": {
      "Hash": 5736779236064664602
    },
    "VoiceID": 80093013
  },
  {
    "ID": 9030402,
    "Sentence": {
      "Hash": 5457147741895186834
    },
    "VoiceID": 80093014
  },
  {
    "ID": 9030403,
    "Sentence": {
      "Hash": 8581635328606303244
    },
    "VoiceID": 80093015
  },
  {
    "ID": 9030404,
    "Sentence": {
      "Hash": 8827375485204097595
    },
    "VoiceID": 80093016
  },
  {
    "ID": 9030405,
    "Sentence": {
      "Hash": 7188082195556370217
    },
    "VoiceID": 80093017
  },
  {
    "ID": 9030501,
    "Sentence": {
      "Hash": 17500238443165905287
    },
    "VoiceID": 80093018
  },
  {
    "ID": 9030502,
    "Sentence": {
      "Hash": 16078318358652191398
    },
    "VoiceID": 80093019
  },
  {
    "ID": 9030503,
    "Sentence": {
      "Hash": 15705668496848618772
    },
    "VoiceID": 80093020
  },
  {
    "ID": 9030504,
    "Sentence": {
      "Hash": 18379528699777855175
    },
    "VoiceID": 80093021
  },
  {
    "ID": 11010101,
    "Sentence": {
      "Hash": 16593878175648518966
    },
    "VoiceID": 80111001
  },
  {
    "ID": 11010102,
    "Sentence": {
      "Hash": 2527030280353787788
    },
    "VoiceID": 80111002
  },
  {
    "ID": 11010103,
    "Sentence": {
      "Hash": 4636749190353992439
    },
    "VoiceID": 80111003
  },
  {
    "ID": 11010104,
    "Sentence": {
      "Hash": 8069185799710844711
    },
    "VoiceID": 80111004
  },
  {
    "ID": 11010201,
    "Sentence": {
      "Hash": 10127665941390063580
    },
    "VoiceID": 80111005
  },
  {
    "ID": 11010202,
    "Sentence": {
      "Hash": 5213431463385745911
    },
    "VoiceID": 80111006
  },
  {
    "ID": 11010203,
    "Sentence": {
      "Hash": 8378612498896204636
    },
    "VoiceID": 80111007
  },
  {
    "ID": 11010301,
    "Sentence": {
      "Hash": 10311769328665483033
    },
    "VoiceID": 80111008
  },
  {
    "ID": 11010302,
    "Sentence": {
      "Hash": 11189063081702982242
    },
    "VoiceID": 80111009
  },
  {
    "ID": 11010303,
    "Sentence": {
      "Hash": 13725701767745643193
    },
    "VoiceID": 80111010
  },
  {
    "ID": 11010304,
    "Sentence": {
      "Hash": 15275688972116699038
    },
    "VoiceID": 80111011
  },
  {
    "ID": 11010401,
    "Sentence": {
      "Hash": 17813573121673256142
    },
    "VoiceID": 80111012
  },
  {
    "ID": 11010402,
    "Sentence": {
      "Hash": 6959787937481628508
    },
    "VoiceID": 80111013
  },
  {
    "ID": 11010403,
    "Sentence": {
      "Hash": 10903556171144739342
    },
    "VoiceID": 80111014
  },
  {
    "ID": 11010404,
    "Sentence": {
      "Hash": 7254968117577776263
    },
    "VoiceID": 80111015
  },
  {
    "ID": 11010501,
    "Sentence": {
      "Hash": 13896930887557533763
    },
    "VoiceID": 80111016
  },
  {
    "ID": 11010502,
    "Sentence": {
      "Hash": 2581604252901793680
    },
    "VoiceID": 80111017
  },
  {
    "ID": 11010503,
    "Sentence": {
      "Hash": 4578686398291091553
    },
    "VoiceID": 80111018
  },
  {
    "ID": 11010504,
    "Sentence": {
      "Hash": 2296982138759173963
    },
    "VoiceID": 80111019
  }
]